[
  {
    "name": "Curry Riz Lentille",
    "description": "Un plat chaud et réconfortant",
    "ingredients": [
      {
        "name": "Riz",
        "quantity": 200,
        "unit": "grammes",
        "gramsPerUnit": "1",
        "Kcal": "130"
      },
      {
        "name": "Nouilles",
        "quantity": 20
      },
      {
        "name": "Riz",
        "quantity": 20,
        "unit": "grammes",
        "gramsPerUnit": "1",
        "Kcal": "130"
      }
    ],
    "totalKcal": 312,
    "totalWeight": 240
  },
  {
    "name": "gouter",
    "description": "",
    "ingredients": [
      {
        "name": "pain",
        "quantity": 40
      },
      {
        "name": "chocolat",
        "quantity": 1
      }
    ],
    "totalKcal": 610,
    "totalWeight": 1300
  }
]